pywinschedule/__init__.py
pywinschedule/config.py
pywinschedule/nssm_service.py
pywinschedule/pywin32_service.py
pywinschedule/run_once_a_day.py
pywinschedule/watcher.py
pywinschedule/windows_task_scheduler.py
pywinschedule/clitools/__init__.py
pywinschedule/clitools/cli.py
pywinschedule/data/nssm.exe
pywinschedule/utils/__init__.py
pywinschedule/utils/admin.py
pywinschedule/utils/dbutils.py
pywinschedule/utils/ipc.py
pywinschedule/utils/process.py
pywinschedule/utils/sqlitekvstore.py
pywinschedule-0.0.6.9.dist-info/LICENSE
pywinschedule-0.0.6.9.dist-info/METADATA
pywinschedule-0.0.6.9.dist-info/WHEEL
pywinschedule-0.0.6.9.dist-info/entry_points.txt
pywinschedule-0.0.6.9.dist-info/top_level.txt
pywinschedule-0.0.6.9.dist-info/RECORD
