Metadata-Version: 2.1
Name: pywinschedule
Version: 0.0.6.9
Summary: Schedule script with windows task scheduler
Home-page: http://gitee.com/peiiii/pywinschedule
Author: Wang Pei
Author-email: 1535376447@qq.com
License: UNKNOWN
Platform: UNKNOWN
Classifier: Programming Language :: Python :: 3
Classifier: License :: OSI Approved :: MIT License
Classifier: Operating System :: OS Independent
Requires-Python: >=3.0
License-File: LICENSE
Requires-Dist: pywin32
Requires-Dist: python-dateutil
Requires-Dist: watchdog
Requires-Dist: fire
